floopy/__init__.py
floopy/basesystem.py
floopy/datamanager.py
floopy/pathnode.py
floopy-0.1.2.dist-info/LICENSE
floopy-0.1.2.dist-info/METADATA
floopy-0.1.2.dist-info/WHEEL
floopy-0.1.2.dist-info/top_level.txt
floopy-0.1.2.dist-info/RECORD
