Metadata-Version: 2.1
Name: floopy
Version: 0.1.2
Summary: Tester-Agnostic Sequencer for Hardware-Testing in Python
Author-email: Friedrich Hagedorn <friedrich_h@gmx.de>
License: GPL 3
Project-URL: Homepage, https://github.com/floopy-systems/floopy
Keywords: test,sequencer,task,loop,sweep
Requires-Python: >=3.10
License-File: LICENSE
Requires-Dist: numpy
Requires-Dist: pandas
Requires-Dist: collection
Requires-Dist: jsonpickle
Requires-Dist: tzlocal
Requires-Dist: getmac
Requires-Dist: rich
